spike/FTICR.py
spike/FTMS.py
spike/NPKConfigParser.py
spike/NPKData.py
spike/NPKError.py
spike/Orbitrap.py
spike/Tests.py
spike/__init__.py
spike/dev_setup.py
spike/processing.py
spike/version.py
spike/version_rev.py
spike/Algo/BC.py
spike/Algo/CS_transformations.py
spike/Algo/Cadzow.py
spike/Algo/Cadzow_mpi.py
spike/Algo/Cadzow_mpi2.py
spike/Algo/Laplace.py
spike/Algo/Linpredic.py
spike/Algo/SL0.py
spike/Algo/SL0_test.py
spike/Algo/__init__.py
spike/Algo/maxent.py
spike/Algo/rQRd.py
spike/Algo/sane.py
spike/Algo/sane_old.py
spike/Algo/savitzky_golay.py
spike/Algo/urQRd.py
spike/Display/__init__.py
spike/Display/fakeplot.py
spike/Display/testplot.py
spike/File/Apex.py
spike/File/BrukerMS.py
spike/File/BrukerNMR.py
spike/File/BrukerSMX.py
spike/File/GifaFile.py
spike/File/HDF5File.py
spike/File/Solarix.py
spike/File/Spinit.py
spike/File/Spinit_with2D.py
spike/File/Thermo.py
spike/File/__init__.py
spike/File/csv.py
spike/File/mzXML.py
spike/Interactive/FTICR_INTER.py
spike/Interactive/INTER.py
spike/Interactive/__init__.py
spike/Miscellaneous/__init__.py
spike/Miscellaneous/big.py
spike/Miscellaneous/bruker_corr.py
spike/Miscellaneous/downsample.py
spike/Miscellaneous/downsampling.py
spike/Miscellaneous/poulding.py
spike/Miscellaneous/processing2.py
spike/Miscellaneous/stat.py
spike/plugins/Bruker_NMR_FT.py
spike/plugins/Bucketing.py
spike/plugins/FTMS_calib.py
spike/plugins/Fitter.py
spike/plugins/Linear_prediction.py
spike/plugins/PALMA.py
spike/plugins/Peaks.py
spike/plugins/__init__.py
spike/plugins/apmin.py
spike/plugins/bcorr.py
spike/plugins/bokeh_display.py
spike/plugins/fastclean.py
spike/plugins/gaussenh.py
spike/plugins/pg_sane.py
spike/plugins/rem_ridge.py
spike/plugins/sane.py
spike/plugins/sg.py
spike/plugins/test.py
spike/plugins/tisane.py
spike/plugins/urQRd.py
spike/plugins/wavelet.py
spike/plugins/zoom3D.py
spike/util/ConfigForm.py
spike/util/ValErr.py
spike/util/__init__.py
spike/util/compat.py
spike/util/counter.py
spike/util/debug_tools.py
spike_py-0.99.7.dist-info/LICENSE
spike_py-0.99.7.dist-info/METADATA
spike_py-0.99.7.dist-info/WHEEL
spike_py-0.99.7.dist-info/top_level.txt
spike_py-0.99.7.dist-info/RECORD
