Metadata-Version: 2.1
Name: spike-py
Version: 0.99.7
Summary: The SPIKE program. A collaborative development for a FT-spectroscopy processing program
Home-page: https://bitbucket.org/delsuc/spike
Author: M-A. Delsuc
Author-email: madelsuc@unistra.fr
License: CeCILL-2.1
Platform: UNKNOWN
Classifier: Programming Language :: Python
Classifier: License :: OSI Approved :: CEA CNRS Inria Logiciel Libre License, version 2.1 (CeCILL-2.1)
Classifier: Operating System :: OS Independent
Classifier: Intended Audience :: Science/Research
Classifier: Topic :: Scientific/Engineering :: Chemistry
Requires: matplotlib
Requires: numpy
Requires: scipy
Requires: tables
Provides: spike
